shinami_python_sdk/__init__.py
shinami_python_sdk/exceptions.py
shinami_python_sdk/iaw.py
shinami_python_sdk/models.py
shinami_python_sdk-0.2.0.dist-info/LICENSE
shinami_python_sdk-0.2.0.dist-info/METADATA
shinami_python_sdk-0.2.0.dist-info/WHEEL
shinami_python_sdk-0.2.0.dist-info/RECORD
