Metadata-Version: 2.1
Name: shinami-python-sdk
Version: 0.2.0
Summary: This library provides easy access to Shinami APIs.
Author: Studio Mirai, LLC
Author-email: os@sm.xyz
Requires-Python: >=3.11,<4.0
Classifier: Programming Language :: Python :: 3
Classifier: Programming Language :: Python :: 3.11
Requires-Dist: httpx (>=0.24.1,<0.25.0)
Requires-Dist: pydantic (>=2.1.1,<3.0.0)
